fastclip/__init__.py
fastclip-0.2.dist-info/LICENSE.txt
fastclip-0.2.dist-info/METADATA
fastclip-0.2.dist-info/WHEEL
fastclip-0.2.dist-info/top_level.txt
fastclip-0.2.dist-info/RECORD
