Metadata-Version: 2.1
Name: fastclip
Version: 0.2
Summary: A private library for fastclip
Home-page: https://github.com/fastclip/library
Download-URL: https://github.com/fastclip/library/archive/v_02.tar.gz
Author: Fastclip
Author-email: hello+pip@fastclip.io
License: MIT
Keywords: fastclip
License-File: LICENSE.txt
Requires-Dist: typing-extensions
Requires-Dist: pydantic
